[{"senderKeyId":161175990,"senderChainKey":{"iteration":86,"seed":"yDJIyAjI4hgtl892JqbH0KfY0wb7UfiU65c/+dg1sxg="},"senderSigningKey":{"public":"BRpGBMoZ7SB3YWiSqWsBKroJWyE/1ElmHCiqK+icO/ZE"},"senderMessageKeys":[]},{"senderKeyId":1972248941,"senderChainKey":{"iteration":79,"seed":"LtrInkouwWflTnRoyMOkvXhCn+YdkQKlX774/NR6H8A="},"senderSigningKey":{"public":"BUkPkBYmqngqdPlhrIikoTmrcq0E06LonGzJoVad6IY4"},"senderMessageKeys":[]},{"senderKeyId":559790927,"senderChainKey":{"iteration":20,"seed":"VlwO9yNXna3rX9GBcir7emR46/TNeRHeFWH8umRKWBQ="},"senderSigningKey":{"public":"BZ3l6v8/6H0uQNsfmdvm64oAuucr3KhUJl7ywoMiYsh2"},"senderMessageKeys":[]},{"senderKeyId":579524544,"senderChainKey":{"iteration":22,"seed":"u1L8VqWdyhdcD74FRSS2lLxYnngPB5X02Q7zcrky0Lg="},"senderSigningKey":{"public":"BSxDh83ukPdSDu7GR35D/1cYGi0y4RKDBWa/bWTl2EIP"},"senderMessageKeys":[]},{"senderKeyId":453942994,"senderChainKey":{"iteration":446,"seed":"bCLg054g7nuN08K+QGnYipIy+Tt2A5Cm3+wSR1VXB98="},"senderSigningKey":{"public":"BeMfWSBtReAhLL6qukIQ/RwVgDK1VvavqN4OSxlKiX8K"},"senderMessageKeys":[{},{},{},{},{},{},{},{},{},{},{},{},{},{},{},{},{},{},{},{},{},{},{},{},{},{},{},{},{},{},{},{},{},{},{},{},{},{},{},{},{},{},{},{},{},{},{},{},{},{},{},{},{},{},{},{},{},{},{},{},{},{},{},{},{},{},{},{},{},{},{},{},{},{},{},{},{},{},{},{},{},{},{},{},{},{},{},{},{},{},{},{},{},{},{},{},{},{},{},{},{},{},{},{},{},{},{},{},{},{},{},{},{},{},{},{},{},{},{},{},{},{},{},{},{},{},{},{},{},{},{},{},{},{},{},{},{},{},{},{},{},{},{},{},{},{},{},{},{},{},{},{},{},{},{},{},{},{},{},{},{},{},{},{},{},{},{}]}]